Workbook

Sheet Location Data
A1: LOCATION DATA:
A2: Information provided should be an exact match to the business name found on the location's Google Business Profile.
A3: CURRENT BUSINESS NAME: | B3: Infinity Technology Consulting, Inc | D3: PREVIOUS BUSINESS NAME(S):
A4: CURRENT BUSINESS ADDRESS: | B4: 1040 Boulevard SE suite H, Atlanta, GA 30312, United States | D4: PREVIOUS BUSINESS ADDRESS(ES):
A5: CURRENT BUSINESS PHONE NUMBER: | B5: =17703066989 -> 17703066989 | D5: PREVIOUS BUSINESS PHONE NUMBER(S):
A6: CURRENT BUSINESS WEBSITE URL: | B6: https://infinitytechconsulting.com/ | D6: PREVIOUS BUSINESS WEBSITE URL(S):
A7: BUSINESS OWNER'S NAME: | B7: Infinity Technology Consulting, Inc. (Infinity) is 20-year IT Enterprise Cloud and Managed Services Provider | D7: NOTES:
A8: BUSINESS EMAIL: | B8: https://infinitytechconsulting.com/
A9: BUSINESS CATEGORIES: | B9: Computer consultant, Computer support and services
A10: BUSINESS DESCRIPTION (SHORT):
A11: BUSINESS DESCRIPTION (LONG):
A12: OPENING/FOUNDED DATE:
A13: HOURS OF OPERATION: | B13: Mon-Friday | C13: 9 am–5 pm
B14: Saturday | C14: Closed
B15: Sunday | C15: Closed
A17: TOP 5 KEYWORDS:
A18: PRODUCT INFORMATION:
A19: IMAGE ASSETS:
A20: GOOGLE BUSINESS PROFILE (GBP) URL: | B20: Infinity Technology Consulting, Inc
A21: VERIFIED?
A22: LAST CHECKED
A23: GMB Services | B23: Computer Consultant (category) • IT consulting • IT Managed Services Provider • Bandwidth Management • Cable Installation • Client Portal • Cloud Monitoring • Cloud Solutions • Consulting Support • Cyber Security • Data Backup • Email Filtering • I T Project Management • Management Anti • Monthly Managed Services • Network Design & Implementation • Network Monitoring • Network Penetration Testing • Network Segmentation • Onsite Support • Patch Management • Physical Design • Privileged Access Management • Security Awareness Training • Strategic Consulting • Tech Consulting • Technology Consulting • User Account Management • Vulnerability Assessment • Wireless Survey

Sheet Citation Audit
B1: CITATION AUDIT
B2: A citation audit is done to identify (a) where you have and don't have citations, (b) whether or not they are correct and (c) what may need to be corrected. Awareness of your citation profile will lead to better decision making (i.e. citation building, cleaning) and result in better Google Business Profile rankings.
B3: CITATION AUDIT SUMMARY
B4: TOTAL EXISTING CITATIONS: | C4: 8
B5: TOTAL CORRECT CITATIONS: | C5: 0
B6: TOTAL INACCURATE / DUPLICATE CITATIONS: | C6: 8
B7: FINDINGS/ISSUES: | C7: 8 total citations identified. 0 correct citations — no accurate foundation. 8 inaccurate/duplicate citations, making all listings inconsistent.
B8: RECOMMENDATIONS/SOLUTIONS: | C8: Immediate citation cleanup is needed to correct or remove all 33 inaccurate listings. After cleanup, build accurate citations to establish a proper base. Maintain consistency with regular audits and monitoring going forward.
B10: Aggregators
B11: Local data aggregators are large business focused entitites that distribute local business data to other entities like local business directories. If your business information is incorrect with an aggregator, commonly it is also incorrect in many other places. Nip it in the bud at the source, and you can mitigate further spread, as well as correct many of the existing, incorrect instances.
B13: Profile URL | C13: DR | D13: Business Name | E13: Address | F13: Phone | G13: URL | H13: Indexation | I13: Status
B14: No Aggregators found
B16: Citations Discovered
B17: Below are instances of your indexed location data found in Google. In some cases we found elements of your business data, without the rest, resulting in "not found". We also try to find data that is a partial match to data provided, this would be marked "incorrect".
B19: MASTER | C19: - | D19: Infinity Technology Consulting Inc | E19: 1040 Boulevard Se Ste H, Atlanta, Georgi... | F19: (770) 306-6989 | H19: Yes | I19: Correct NAP
A20: # | B20: Platform | C20: Profile URL | D20: Business Name Listed | E20: Address Listed | F20: Phone Listed | G20: Website/URL | H20: Indexation | I20: NAP Status | J20: Action Required
A21: 1 | B21: Bloomberg | C21: https://www.bloomberg.com/profile/company/0087024D:US | D21: Infinity Technology Consulting Inc | E21: 1040 Blvd Se Suite H, Atlanta, GA 30312, United States | F21: Not found | G21: infinitytechconsulting.com | H21: Yes | I21: ✗ Mismatch / Missing | J21: Incorrect Address — 'Blvd' should be 'Boulevard'
A22: 2 | B22: Procore | C22: https://network.procore.com/p/infinity-technology-consulting-atlanta | D22: Infinity Technology Consulting | E22: 1040 Boulevard Dr SE, Atlanta, GA | F22: (770) 306-6989 | G22: Not found | H22: Yes | I22: ⚠ Incomplete | J22: Minor address variation — 'Dr SE' should be 'SE'; URL missing
A23: 3 | B23: CBInsights | C23: https://www.cbinsights.com/company/infinity-technology-consulting | D23: Infinity Technology Consulting | E23: 1040 Boulevard SE Suite H, Atlanta, Georgia 30312, United States | F23: Not found | G23: https://infinitytechconsulting.com/ | H23: Yes | I23: ⚠ Incomplete | J23: Phone not listed — otherwise NAP consistent
A24: 4 | B24: ZoomInfo | C24: https://www.zoominfo.com/c/infinity-technology-consulting-inc/346579921 | D24: Infinity Technology Consulting | E24: 1040 Boulevard Se Ste H, Atlanta, Georgia 30312 | F24: (770) 306-6989 | G24: https://infinitytechconsulting.com/ | H24: Yes | I24: ✓ Correct NAP | J24: Consistent NAP ✓
A25: 5 | B25: LinkedIn | C25: https://www.linkedin.com/company/infinity-technology-consulting-inc | D25: Infinity Technology Consulting, Inc. | E25: 1040 Boulevard SE Suite H, Atlanta, Georgia 30312, United States | F25: Not found | G25: https://infinitytechconsulting.com/ | H25: Yes | I25: ⚠ Incomplete | J25: Phone not listed — otherwise NAP consistent
A26: 6 | B26: MapQuest | C26: https://www.mapquest.com/us/georgia/infinity-technology-consulting-411140992 | D26: Infinity Technology Consulting | E26: 3595 Renaissance Cir, Atlanta, GA 30349 | F26: 1 (770) 306-6989 | G26: https://infinitytechconsulting.com/ | H26: Yes | I26: ✗ Mismatch / Missing | J26: WRONG ADDRESS — old/stale address; needs urgent correction
A27: 7 | B27: IPComm / Portfolio | C27: https://weareipcomm.com/works/infinity-technology-consulting/ | D27: Infinity Technology Consulting | E27: Not found | F27: (770) 306-6989 | G27: Not found | H27: Yes | I27: ⚠ Incomplete | J27: Address and website not listed
A28: 8 | B28: Indeed | C28: https://www.indeed.com/cmp/Infinity-Technology-Consulting | D28: Infinity Technology Consulting | E28: Not found | F28: Not found | G28: Not found | H28: Yes | I28: ⚠ Incomplete | J28: Address, phone, and website all missing
A29: 9 | B29: Yelp | C29: https://www.yelp.com/biz/infinity-technology-consulting-atlanta | D29: Infinity Technology Consulting | E29: 3595 Renaissance Cir, Atlanta, GA | F29: (770) 306-6989 | G29: infinitytechconsulting.com | H29: Yes | I29: ✗ Mismatch / Missing | J29: WRONG ADDRESS — stale address indexed; urgent fix needed
A30: 10 | B30: Nextdoor | C30: https://nextdoor.com/pages/infinity-technology-consulting-atlanta-ga | D30: Infinity Technology Consulting | E30: 3595 Renaissance Cir, Atlanta, GA 30349 | F30: +1 (770) 306-6989 | G30: Not found | H30: Yes | I30: ✗ Mismatch / Missing | J30: WRONG ADDRESS — stale address; update to 1040 Boulevard SE
A31: 11 | B31: Yahoo Local | C31: https://local.yahoo.com/info-153142939-infinity-technology-consulting-atlanta | D31: Infinity Technology Consulting | E31: 1040 Boulevard SE, #H, Atlanta GA 30312 | F31: (770) 306-6989 | G31: infinitytechconsulting.com | H31: Yes | I31: ✓ Correct NAP | J31: Consistent NAP ✓
A32: 12 | B32: Black Directory | C32: https://www.blackdirectory.com/georgia/atlanta/information-technology/infinity-technology-consulting-inc | D32: Infinity Technology Consulting Inc. | E32: 1040 Boulevard SE, Suite H, Atlanta GA 30312 | F32: (770) 306-6989 | G32: infinitytechconsulting.com | H32: Yes | I32: ✓ Correct NAP | J32: Consistent NAP ✓
... A35: 15 | B35: BBB | C35: https://www.bbb.org | D35: Not listed | E35: — | F35: — | G35: — | H35: No | I35: ✗ Mismatch / Missing | J35: NO LISTING — high-authority citation; must be claimed
A38: SUMMARY STATS
A39: Total Citations Found: | B39: 16
A40: Correct NAP: | B40: 3
A41: Wrong / Stale Address: | B41: 4
A42: Incomplete (phone/URL missing): | B42: 6
A43: No Listing (must build): | B43: 1
A44: Needs Manual Verification: | B44: 1

Sheet Compare with Competitors
A1: =HYPERLINK("https://daltonluka.com/", Image("https://daltonluka.com/wp-content/uploads/2020/10/horizontal-logo-white.png"))
A2: Google My Business Audit | C2: Infinity Technology Consulting, Inc | E2: Southeastern Computer Associates | IT Services Atlanta | F2: Network 1 Consulting - Atlanta Managed IT Services Company | G2: TrueITPros
A3: Type | B3: Check | C3: Infinity Technology Consulting, Inc. | E3: https://maps.app.goo.gl/neTAb9SRQkkWR4497 | F3: https://maps.app.goo.gl/fdnGe1YZe9jhS7BZA | G3: https://maps.app.goo.gl/BAqMSDvuXUvpGwbR7
A4: Target query = {Computer consultant in Atlanta} | D4: Need to Update | E4: Target Locality = {Atlanta, GA}
A5: Address | C5: 1040 Boulevard SE suite H, Atlanta, GA 30312, United States | E5: 3715 Northside Pkwy NW Bldg. 100 - Suite 500A,Atlanta, GA 30327,United States | F5: 3355 Lenox Rd NE Suite 754,Atlanta, GA 30326,United States | G5: 260 Peachtree St NW Suite 2200, Atlanta, GA 30303, United States
A6: Phone Number | C6: =17703066989 -> 17703066989 | E6: =16788373954 -> 16788373954 | F6: =14049993504 -> 14049993504 | G6: =14049993504 -> 14049993504
A8: Proximity Audit
A9: Manual Review | B9: Target Locality in Listing Address | C9: Yes | E9: Yes | F9: Yes | G9: Yes
A10: Relevance Audit
A11: Manual Review | B11: Keyword in Listing Title | C11: No | E11: Yes | F11: Yes | G11: Yes
A12: Manual Review | B12: Locality in Listing Title | C12: No | E12: Yes | F12: Yes | G12: Yes
A13: Manual Review | B13: Primary Category | C13: Computer consultant | E13: Computer Consultant | F13: Computer Support and Services | G13: Computer Support and Services
A14: Manual Review | B14: Category #2 | C14: Computer support and services | E14: Business to Business Service | F14: Computer Consultant | G14: Business to Business Service
A15: Manual Review | B15: Category #3 | E15: Computer Repair Service | F15: Computer Security Service | G15: Computer Consultant
A16: Manual Review | B16: Category #4 | E16: Computer Service | F16: Computer Service | G16: Computer Security Service
A17: Manual Review | B17: Category #5 | E17: Computer Support and Services | F17: Data Recovery Service | G17: Computer Service
A18: Manual Review | B18: Category #6 | E18: Computer Wholesaler | G18: Internet Marketing Service
A19: Manual Review | B19: Website URL | C19: https://infinitytechconsulting.com/ | E19: https://sca-atl.com/ | F19: https://network1consulting.com/managed-it-services-atlanta/ | G19: http://trueitpros.com/
A20: Schema Validator | B20: Has LocalBusiness Markup | C20: No | E20: Yes | F20: No | G20: No
A21: Hours of Operation
B22: Mon-Friday | C22: 9 am–5 pm | E22: Mon,Tue,Fri = 8am-5pm | F22: This business has not provided business hours | G22: 7AM-4PM
B23: Saturday | C23: Closed | E23: Sat=10am-7pm | G23: Closed
B24: Sunday | C24: Closed | E24: Sun=12-7pm | G24: Closed
A25: Description | D25: Need to Optimized | E25: Southeastern Computer Associates (SCA) provides the best IT Support for Metro Atlanta and all of Georgia, if you are a business owner or school administrator looking for an alternative to hiring employees, or if you are not happy with the level of IT Support Atlanta that you are currently receiving from another IT Support Provider in Atlanta, please give us a call for a no cost consultation. Experience the best IT support Atlanta has to offer. We offer a wide variety of IT services ranging from data protection, cyber security, backup and disaster recovery (ransomware). We have a proven history of working with businesses, charter schools, and non-profits. We're honored to be the highest and most reviewed IT company in Atlanta and Georgia! | F25: For more than two decades, we’ve built Network 1 to be your partner and a home for IT that simply works. Our clients know they can depend on us to provide the best managed IT services in Atlanta they need to run their businesses efficiently and effectively. Our Atlanta computer support makes sure our clients never have to worry whether they have the best systems in place for their specific needs, freeing them up so they can focus on the tasks that bring the most value to their clients, employees and stakeholders. Our Atlanta IT company covers all the necessary requirements under one IT vendor. | G25: At Downtown Atlanta Dentistry, we are committed to helping our community achieve healthy, comfortable, and radiant smiles. Our patient-centered approach is built on trust and open communication, fostering lasting relationships with each patient. Our skilled dentists utilize modern facilities and advanced techniques to provide high-quality care in a welcoming environment. We prioritize your safety, comfort, and education, ensuring you are well-informed and comfortable throughout your treatment. With efficient and gentle visits tailored to your needs, we aim to deliver exceptional service at fair prices. Book Your Appointment Today!
A32: Areas Served | C32: No | E32: Yes | F32: Yes | G32: Yes
A34: Replies to Reviews | C34: No | E34: Yes | F34: No | G34: No
A35: Nos. of Posts | C35: No | E35: No | F35: No | G35: Last 2 months 2 posts
A36: Q & A Optimized? | C36: Yes | E36: Yes | F36: No | G36: No
A37: Nos. of Pics Uploaded | C37: No | E37: Yes | F37: Yes | G37: Yes
A38: Type of Images | C38: No
A39: Using Videos? | C39: No | E39: Yes | F39: No | G39: No
A40: Prominence Audit
A41: Manual Review | B41: Review Count | C41: No | E41: Yes | F41: Yes | G41: 753
A42: Manual Review | B42: Star Rating | C42: No | E42: Yes | F42: Yes | G42: 4.7
A43: Manual Review | B43: Has Featured 3rd Party Reviews | C43: No | E43: Yes | F43: No | G43: No
A44: Manual Review | B44: Has Featured Social Profiles | C44: No | E44: Yes | F44: Yes | G44: Yes

Sheet Audit
A1: Business Information Accuracy | B1: Status | C1: Notes | D1: Services Optimization | E1: Status | F1: Notes | G1: Product Section | H1: Status | I1: Notes
A2: Business Name correct | B2: Yes | D2: All services added | E2: No | G2: Products added | H2: No | I2: Need to Add More Products. The products aren’t added properly
A3: Category correct | B3: No | D3: Service descriptions under 300 characters | E3: Yes | G3: Service descriptions under 300 characters | H3: No
A4: Secondary Category set | B4: Yes | D4: Descripton Optimization | E4: No | G4: Descripton Optimization | H4: No
A5: Address correct | B5: Yes | D5: Natural wording used | E5: No | G5: Images added | H5: No | I5: Need to use geo tagged Original images
A6: Service Area set properly | B6: No | D6: Price ranges added | E6: No | G6: CTA buttons used | H6: No
A7: Phone Number correct | B7: Yes | D7: Categories match services | E7: No | G7: No promotional spam language | H7: No
A8: Website added | B8: Yes | D8: Website added | E8: No
A9: Business hours accurate | B9: Yes | D9: Business hours accurate | E9: No
A10: Booking Link Added | B10: No | D10: Holiday hours updated | E10: No
A11: Business opening / founding date | B11: No
A12: GMB Description Optimized | B12: No | C12: Description need to optimized keep it to localized
A13: Perform competitor audit | C13: Check Nexct Tab
A14: Photo Audit | B14: Status | C14: Notes | D14: Reviews and Reputation | E14: Status | F14: Notes | G14: Posts Optimization | H14: Status | I14: Notes
A15: Geo-tagged photos | B15: No | C15: Photos are not geo-tagged, affecting local relevance. | D15: Review responses timely | E15: No | F15: Responses are timely, but can still be improved for consistency. | G15: 2 Weekly posts added | H15: No | I15: posting at least 2 times per week to boost engagement and visibility.
A16: High-quality images | B16: No | C16: Current images lack quality and clarity. | D16: Review Optimized | E16: No | F16: Reviews are not optimized; no keyword-rich or detailed feedback. | G16: Job updates posted | H16: No | I16: No job updates are shared. Recommend posting recent projects to build trust and show activity.
A17: Before and after work | B17: No | C17: No before/after photos uploaded to showcase work. | D17: Keyword in reviews | E17: No | F17: Customers/Owner are not using service-related keywords in reviews. | G17: Offers posted | H17: No | I17: No offers are posted. Recommend sharing discounts or promotions to attract new customers.
A18: Equipment and Staff photos | B18: No | D18: Negative review handling plan | E18: No | G18: FAQs posted | H18: No
A19: Job site photos | B19: Yes | C19: Some job site photos are uploaded. | G19: Seasonal posts used | H19: No | I19: No seasonal content is used. Recommend using seasonal posts (storms, fall cleanup, summer tips, etc.) to stay relevant.
A20: Consistent uploads | B20: No | C20: Upload frequency is irregular and not consistent. | H20: No
A23: Local SEO Signals | B23: Status | D23: Reviews and Reputation
A24: NAP consistent across web | B24: Yes | D24: Assign team member to ongoing content calendar for posts
A25: Citations updated | B25: No | D25: Assign team member to publish posts
A26: Website matches GMB categories | B26: Yes | D26: Assign team member to regulary upload photos / videos
A27: Local schema added | B27: No | D27: Assign team member to respond to reviews
A28: GMB embedded on website | B28: No | D28: Assign team member to respond to messages
A29: Local backlinks present | B29: Yes | D29: Assign team member to respond to messages
D30: Assign team member to setup keyword tracking

Sheet Cit Gap
B1: Citation Gap Analysis
B3: A citation gap analysis helps us identify citation opportunities that appear to be propelling your Google Business Profile competitors to top spops. We've helped you determine priority by number of intersects, DR and whether or not you already have the citation.
B5: Website | C5: DR | E5: Status | G5: Competitors
B6: maps.apple.com | C6: 97 | G6: =IF(ISNA(VLOOKUP(B6,'Comp Citation'!A:A,1,FALSE)),"NO","YES") -> YES
B7: foursquare.com | C7: 91 | G7: =IF(ISNA(VLOOKUP(B7,'Comp Citation'!A:A,1,FALSE)),"NO","YES") -> YES
B8: yellowpages.com | C8: 90 | G8: =IF(ISNA(VLOOKUP(B8,'Comp Citation'!A:A,1,FALSE)),"NO","YES") -> YES
B9: manta.com | C9: 87 | G9: =IF(ISNA(VLOOKUP(B9,'Comp Citation'!A:A,1,FALSE)),"NO","YES") -> YES
B10: merchantcircle.com | C10: 85 | G10: =IF(ISNA(VLOOKUP(B10,'Comp Citation'!A:A,1,FALSE)),"NO","YES") -> YES
B11: justlanded.com | C11: 72 | G11: =IF(ISNA(VLOOKUP(B11,'Comp Citation'!A:A,1,FALSE)),"NO","YES") -> YES
B12: superpages.com | C12: 85 | G12: =IF(ISNA(VLOOKUP(B12,'Comp Citation'!A:A,1,FALSE)),"NO","YES") -> YES
B13: yellowbook.com | C13: 77 | G13: =IF(ISNA(VLOOKUP(B13,'Comp Citation'!A:A,1,FALSE)),"NO","YES") -> YES
B14: storeboard.com | C14: 78 | G14: =IF(ISNA(VLOOKUP(B14,'Comp Citation'!A:A,1,FALSE)),"NO","YES") -> YES
B15: cortera.com | C15: 61 | G15: =IF(ISNA(VLOOKUP(B15,'Comp Citation'!A:A,1,FALSE)),"NO","YES") -> YES
B16: brownbook.net | C16: 79 | G16: =IF(ISNA(VLOOKUP(B16,'Comp Citation'!A:A,1,FALSE)),"NO","YES") -> YES
B17: dexknows.com | C17: 78 | G17: =IF(ISNA(VLOOKUP(B17,'Comp Citation'!A:A,1,FALSE)),"NO","YES") -> YES
... B34: whatsnearby.com | C34: 27 | G34: =IF(ISNA(VLOOKUP(B34,'Comp Citation'!A:A,1,FALSE)),"NO","YES") -> YES
B35: Brand Boosters / Top Citations
B36: https://biz.yelp.com/ | C36: Yelp Optimization (Domain Email Required to Claim)
B37: www.crunchbase.com | C37: Crunchbase Optimization (Domain Email Required to Claim)
B38: www.monster.com | C38: Monster Profile - Claim and Optimize
B39: www.eventbrite.com | C39: Eventbrite Profile and Event Link
B40: www.bingplaces.com | C40: Bing Places for Business (Claim and Optimize)
B41: appleid.apple.com https://businessconnect.apple.com/ | C41: Apple Maps Connect
B45: Other Suggested Citation Sources
B47: In our research we found a number of local business directories where you've not yet gained inclusion. While they may not have had correlation among comeptitors, these directories met our minimum criteria for a worthwhile citation. We'd recommend you consider submitting to these (or have us do it for you!)
B49: Website | C49: DR | E49: Status
B50: openstreetmap.org | C50: 94
B51: issuu.com | C51: 93
B52: arcgis.com | C52: 92
B53: yandex.com | C53: 91
B54: nextdoor.com | C54: 90
B55: webwiki.com | C55: 78
B56: ebusinesspages.com | C56: 77
B57: callupcontact.com | C57: 76
B58: ec21.com | C58: 75
B59: askmap.net | C59: 74
B60: find-us-here.com | C60: 74
B61: mindmup.com | C61: 73
... B206: businessadsforfree.net | C206: 20
